{
	"name": "Tg_Event",
	"properties": {
		"annotations": [],
		"runtimeState": "Started",
		"pipelines": [
			{
				"pipelineReference": {
					"referenceName": "P_Migrate_Mult_Files_To_Mult_tables",
					"type": "PipelineReference"
				},
				"parameters": {
					"p_folderPath": "@triggerBody().folderPath",
					"p_fileName": "@triggerBody().fileName"
				}
			}
		],
		"type": "BlobEventsTrigger",
		"typeProperties": {
			"blobPathBeginsWith": "/files-landing-zone/blobs/",
			"blobPathEndsWith": ".csv",
			"ignoreEmptyBlobs": true,
			"scope": "/subscriptions/a1d9a437-725c-4dbd-8317-df8176ad8c3a/resourceGroups/MyResourceGroup/providers/Microsoft.Storage/storageAccounts/mystorageaccountde",
			"events": [
				"Microsoft.Storage.BlobCreated"
			]
		}
	}
}